<databaseChangeLog
    xmlns="http://www.liquibase.org/xml/ns/dbchangelog"
    xmlns:xsi="http://www.w3.org/2001/XMLSchema-instance"
    xsi:schemaLocation="http://www.liquibase.org/xml/ns/dbchangelog http://www.liquibase.org/xml/ns/dbchangelog/dbchangelog-3.1.xsd">

    <property name="now" value="now()" dbms="mysql,h2,mariadb"/>
    <property name="now" value="current_timestamp" dbms="postgresql"/>
    <property name="now" value="sysdate" dbms="oracle"/>

    <property name="autoIncrement" value="true" dbms="mysql,h2,postgresql,mariadb"/>
    <property name="autoIncrement" value="false" dbms="oracle"/>

    <property name="floatType" value="real" dbms="postgresql, h2"/>
    <property name="floatType" value="float" dbms="mysql, oracle,mariadb"/>

    <!--
        Change possible length of descriptions
    -->
	<changeSet author="dkefer" id="change_lengths">
    	    <modifyDataType columnName="description" newDataType="text" tableName="REQUIREMENTSKELETON"/>
    	    <modifyDataType columnName="description" newDataType="text" tableName="COLLECTIONCATEGORY"/>
    	    <modifyDataType columnName="description" newDataType="text" tableName="COLLECTIONINSTANCE"/>
    	    <modifyDataType columnName="description" newDataType="text" tableName="TAGCATEGORY"/>
    	    <modifyDataType columnName="description" newDataType="text" tableName="TAGINSTANCE"/>
    	    <modifyDataType columnName="description" newDataType="text" tableName="REQCATEGORY"/>
    	    <modifyDataType columnName="description" newDataType="text" tableName="STATUSCOLUMN"/>
    	    <modifyDataType columnName="description" newDataType="text" tableName="STATUSCOLUMNVALUE"/>
    	    <modifyDataType columnName="description" newDataType="text" tableName="OPTCOLUMNTYPE"/>
    	    <modifyDataType columnName="description" newDataType="text" tableName="OPTCOLUMN"/>
    	    <modifyDataType columnName="description" newDataType="text" tableName="ALTERNATIVESET"/>
    	    <modifyDataType columnName="description" newDataType="text" tableName="PROJECTTYPE"/>
     	    <modifyDataType columnName="content" newDataType="text" tableName="ALTERNATIVEINSTANCE"/>
    	    <modifyDataType columnName="content" newDataType="text" tableName="OPTCOLUMNCONTENT"/>
	</changeSet>
</databaseChangeLog>
